geourban/__init__.py
geourban/formats.py
geourban/services.py
geourban/types.py
geourban-0.1.dist-info/LICENSE
geourban-0.1.dist-info/METADATA
geourban-0.1.dist-info/WHEEL
geourban-0.1.dist-info/top_level.txt
geourban-0.1.dist-info/RECORD
