Metadata-Version: 2.1
Name: geourban
Version: 0.1
Summary: Direct access to simulated spatially enabled traffic grids of urban regions.
Project-URL: Homepage, https://geospatial-ai.de
Project-URL: GitHub, https://github.com/Geospatial-AI-DE/geourban-py
Project-URL: Documentation, https://geourban.readthedocs.io/en/latest
Keywords: geospatial,intelligence,urban,digital twin
Classifier: Programming Language :: Python :: 3
Classifier: License :: OSI Approved :: Apache Software License
Classifier: Operating System :: OS Independent
Requires-Python: >=3.7
License-File: LICENSE
Requires-Dist: georapid
